{"AssemblyVersion":"0.3.0.92436","RootDirectory":{"RelativePath":"/","ChildDirectories":[{"RelativePath":"res","ChildDirectories":[{"RelativePath":"res\\audio","ChildDirectories":[{"RelativePath":"res\\audio\\Low","ChildDirectories":[],"Files":[{"RelativePath":"res\\audio\\Low\\WOWS_GS.bnk","ApplicationFileType":"bnk","Hash":"7197AC6FD806470FF5B827841686C3003C23B6EA"},{"RelativePath":"res\\audio\\Low\\WOWS_PM.bnk","ApplicationFileType":"bnk","Hash":"2FF691B67F050B0F4F7DB4DD04F9F4028F7E9876"},{"RelativePath":"res\\audio\\Low\\WOWS_XP.bnk","ApplicationFileType":"bnk","Hash":"0B8A2E58FECA585920A3800456EACA9A8984F4D1"}]},{"RelativePath":"res\\audio\\High","ChildDirectories":[],"Files":[{"RelativePath":"res\\audio\\High\\WOWS_GS.bnk","ApplicationFileType":"bnk","Hash":"B8814B1A33E908CFF4BD7D5E055A8BBBA36F5A75"},{"RelativePath":"res\\audio\\High\\WOWS_PM.bnk","ApplicationFileType":"bnk","Hash":"5EBB2D15A4724D1E65E33C36556C3D21317143D4"},{"RelativePath":"res\\audio\\High\\WOWS_XP.bnk","ApplicationFileType":"bnk","Hash":"A9DBFB34237A0B352CDDCEA55E94719316A7D2E9"}]},{"RelativePath":"res\\audio\\English(US)","ChildDirectories":[],"Files":[{"RelativePath":"res\\audio\\English(US)\\WOWS_PF.bnk","ApplicationFileType":"bnk","Hash":"F274F68D87AC89331508854C1F1D23D08D082E8C"},{"RelativePath":"res\\audio\\English(US)\\WOWS_SP.bnk","ApplicationFileType":"bnk","Hash":"430FC167F4131096396B27C485CA034A9813D7FD"},{"RelativePath":"res\\audio\\English(US)\\WOWS_UI.bnk","ApplicationFileType":"bnk","Hash":"C766C618019FF4FFD54E7C30F94D51A5C3DA6933"}]}],"Files":[{"RelativePath":"res\\audio\\Init.bnk","ApplicationFileType":"bnk","Hash":"E53F6FEB5C6E3A3283CDAC973AC1D76DC7D68AC6"},{"RelativePath":"res\\audio\\WOWS_DK.bnk","ApplicationFileType":"bnk","Hash":"4FB4B8533782CFE2E521C9DA801E4A23FD61FB41"},{"RelativePath":"res\\audio\\WOWS_MB.bnk","ApplicationFileType":"bnk","Hash":"DA4FB886C759D13E6CAE9C8CC99CEB32EA1F058A"},{"RelativePath":"res\\audio\\WOWS_MU.bnk","ApplicationFileType":"bnk","Hash":"6A3DE60FA4EB69FED622E5CFEBC5264DAEA1E1E9"},{"RelativePath":"res\\audio\\WOWS_SM.bnk","ApplicationFileType":"bnk","Hash":"7E2BFB82C5A9164B8F40B4786C3637647EE9DC69"}]}]}]}}